nvd_search/__init__.py
nvd_search/cli.py
nvd_search/db_populate.py
nvd_search-0.1.4.dist-info/LICENSE
nvd_search-0.1.4.dist-info/METADATA
nvd_search-0.1.4.dist-info/WHEEL
nvd_search-0.1.4.dist-info/entry_points.txt
nvd_search-0.1.4.dist-info/RECORD
