Metadata-Version: 2.1
Name: nvd-search
Version: 0.1.4
Summary: A CLI Tool made with Python to install the NVD database locally and maintain it using MongoDB.
Author: khalil bouzoffara
Author-email: khalil.bouzoffara@ensi-uma.tn
Requires-Python: >=3.10,<4.0
Classifier: Programming Language :: Python :: 3
Classifier: Programming Language :: Python :: 3.10
Classifier: Programming Language :: Python :: 3.11
Classifier: Programming Language :: Python :: 3.12
Requires-Dist: pymongo[srv] (>=4.7.3,<5.0.0)
Requires-Dist: requests (>=2.32.3,<3.0.0)
Requires-Dist: typer (>=0.12,<0.13)
Requires-Dist: typing-extensions (>=4.12.2,<5.0.0)
